darts/__init__.py
darts/logging.py
darts/timeseries.py
darts/ad/__init__.py
darts/ad/utils.py
darts/ad/aggregators/__init__.py
darts/ad/aggregators/aggregators.py
darts/ad/aggregators/and_aggregator.py
darts/ad/aggregators/ensemble_sklearn_aggregator.py
darts/ad/aggregators/or_aggregator.py
darts/ad/anomaly_model/__init__.py
darts/ad/anomaly_model/anomaly_model.py
darts/ad/anomaly_model/filtering_am.py
darts/ad/anomaly_model/forecasting_am.py
darts/ad/detectors/__init__.py
darts/ad/detectors/detectors.py
darts/ad/detectors/iqr_detector.py
darts/ad/detectors/quantile_detector.py
darts/ad/detectors/threshold_detector.py
darts/ad/scorers/__init__.py
darts/ad/scorers/difference_scorer.py
darts/ad/scorers/kmeans_scorer.py
darts/ad/scorers/nll_cauchy_scorer.py
darts/ad/scorers/nll_exponential_scorer.py
darts/ad/scorers/nll_gamma_scorer.py
darts/ad/scorers/nll_gaussian_scorer.py
darts/ad/scorers/nll_laplace_scorer.py
darts/ad/scorers/nll_poisson_scorer.py
darts/ad/scorers/norm_scorer.py
darts/ad/scorers/pyod_scorer.py
darts/ad/scorers/scorers.py
darts/ad/scorers/wasserstein_scorer.py
darts/dataprocessing/__init__.py
darts/dataprocessing/pipeline.py
darts/dataprocessing/dtw/__init__.py
darts/dataprocessing/dtw/_plot.py
darts/dataprocessing/dtw/cost_matrix.py
darts/dataprocessing/dtw/dtw.py
darts/dataprocessing/dtw/window.py
darts/dataprocessing/encoders/__init__.py
darts/dataprocessing/encoders/encoder_base.py
darts/dataprocessing/encoders/encoders.py
darts/dataprocessing/transformers/__init__.py
darts/dataprocessing/transformers/base_data_transformer.py
darts/dataprocessing/transformers/boxcox.py
darts/dataprocessing/transformers/diff.py
darts/dataprocessing/transformers/fittable_data_transformer.py
darts/dataprocessing/transformers/invertible_data_transformer.py
darts/dataprocessing/transformers/mappers.py
darts/dataprocessing/transformers/midas.py
darts/dataprocessing/transformers/missing_values_filler.py
darts/dataprocessing/transformers/reconciliation.py
u8darts-0.38.0.dist-info/licenses/LICENSE
u8darts-0.38.0.dist-info/METADATA
u8darts-0.38.0.dist-info/WHEEL
u8darts-0.38.0.dist-info/top_level.txt
u8darts-0.38.0.dist-info/RECORD
